agent/__init__.py
agent/utils.py
agent/continuous/__init__.py
agent/continuous/seperate/__init__.py
agent/continuous/seperate/ddpg.py
agent/continuous/seperate/ppo.py
agent/discrete/__init__.py
agent/discrete/seperate/__init__.py
agent/discrete/seperate/a2c.py
agent/discrete/seperate/ppo.py
agent/discrete/seperate/vpg.py
tensorflow_rl-0.2.0.dist-info/METADATA
tensorflow_rl-0.2.0.dist-info/RECORD
tensorflow_rl-0.2.0.dist-info/WHEEL
tensorflow_rl-0.2.0.dist-info/top_level.txt
